{
  "updated_at": "2026-06-11T13:10:36.910698+00:00",
  "athlete": {
    "id": 135716013,
    "firstname": "Andres",
    "lastname": "Hinojosa"
  },
  "stats": {
    "recent_ride_totals": {
      "count": 0,
      "distance": 0,
      "moving_time": 0,
      "elapsed_time": 0,
      "elevation_gain": 0,
      "achievement_count": 0
    },
    "all_ride_totals": {
      "count": 1,
      "distance": 0.0,
      "moving_time": 325,
      "elapsed_time": 325,
      "elevation_gain": 0.0
    },
    "recent_run_totals": {
      "count": 16,
      "distance": 119343.6,
      "moving_time": 43422,
      "elapsed_time": 43883,
      "elevation_gain": 704.3,
      "achievement_count": 0
    },
    "all_run_totals": {
      "count": 385,
      "distance": 2489142.6999999983,
      "moving_time": 846689,
      "elapsed_time": 854124,
      "elevation_gain": 5689.799999999998
    },
    "recent_swim_totals": {
      "count": 0,
      "distance": 0,
      "moving_time": 0,
      "elapsed_time": 0,
      "elevation_gain": 0,
      "achievement_count": 0
    },
    "all_swim_totals": {
      "count": 0,
      "distance": 0,
      "moving_time": 0,
      "elapsed_time": 0,
      "elevation_gain": 0
    },
    "ytd_ride_totals": {
      "count": 0,
      "distance": 0,
      "moving_time": 0,
      "elapsed_time": 0,
      "elevation_gain": 0
    },
    "ytd_run_totals": {
      "count": 70,
      "distance": 481804,
      "moving_time": 167290.0,
      "elapsed_time": 170236.0,
      "elevation_gain": 1800.7999999999997
    },
    "ytd_swim_totals": {
      "count": 0,
      "distance": 0,
      "moving_time": 0,
      "elapsed_time": 0,
      "elevation_gain": 0
    }
  },
  "recent_runs": [
    {
      "resource_state": 2,
      "athlete": {
        "id": 135716013,
        "resource_state": 1
      },
      "name": "Evening Run",
      "distance": 8139.1,
      "moving_time": 2664,
      "elapsed_time": 2678,
      "total_elevation_gain": 10.0,
      "type": "Run",
      "sport_type": "Run",
      "workout_type": null,
      "device_name": "Apple Watch Series 10",
      "id": 18871243553,
      "start_date": "2026-06-10T22:08:10Z",
      "start_date_local": "2026-06-10T18:08:10Z",
      "timezone": "(GMT-05:00) America/New_York",
      "utc_offset": -14400.0,
      "location_city": null,
      "location_state": null,
      "location_country": null,
      "achievement_count": 26,
      "kudos_count": 2,
      "comment_count": 0,
      "athlete_count": 1,
      "photo_count": 0,
      "map": {
        "id": "a18871243553",
        "summary_polyline": "oyvwFfmubM]~@?VDFd@Th@L\\?VJJNFh@JJjB\\xGrB~@VfARz@XJFCPO^Qt@oAvDCJBLFDNCHGHMH_@b@cAT{@t@kBFGZ?NF^\\Fp@LLp@T`@FbAXd@RDPEr@?nBH^PRJ?BGFc@JyDJcADmBBQBGDC\\F`BBn@WVARDd@V\\Lb@JZDLCn@UXCTD\\R^l@NHJCf@Sl@Ob@WNMHk@@EFEX?rC^BB@FAx@FZJFf@@B`DGnBCp@QrAGx@Bh@DFTFL?HGBEBc@R}@?eAHyA@gABYHe@FoA@CZ?JEHc@Ts@FGH?~ARh@Nl@DtAVx@DnARb@LjAv@d@Tf@LrAd@dAPfDDXDnCHXDt@DpDFr@?dBLbB@|@Lt@@jBNhADh@?ZBf@AtANt@Bp@H`@AfAFz@@~ALJFBHEp@BfBExEQ`EBHB@XIZ@b@AlD^fAB`@D`@A@{BFcAJwENgCFa@DC\\FtC@lALpADrBN|Dl@|@Dx@@\\LpATtD^|@Tt@Dj@L_AGu@Qu@Kg@AcAIuCe@eCUaC_@wC[oH]c@Ga@@y@Kc@?_AIeBCcC[[AsABqI[mCGOCk@]MCOBQNU@mAGe@?yAMqEUsB@mBQ{BEi@E}@C_@@gAIsBGUGm@YgA_@w@OcAo@UK}AW[KqDg@k@Qc@AUC}D}@SC]Au@FiCOa@Oc@E_@K_AQ}Bi@uAK{ADyB[",
        "resource_state": 2
      },
      "trainer": false,
      "commute": false,
      "manual": false,
      "private": false,
      "visibility": "everyone",
      "flagged": false,
      "gear_id": "g24214689",
      "start_latlng": [
        40.754324,
        -74.006756
      ],
      "end_latlng": [
        40.747807,
        -74.008135
      ],
      "average_speed": 3.055,
      "max_speed": 5.28,
      "average_watts": 184.4,
      "max_watts": 250,
      "weighted_average_watts": 185,
      "device_watts": true,
      "kilojoules": 491.1,
      "has_heartrate": true,
      "average_heartrate": 171.1,
      "max_heartrate": 190.0,
      "heartrate_opt_out": false,
      "display_hide_heartrate_option": true,
      "elev_high": 6.8,
      "elev_low": -1.2,
      "upload_id": 19983006748,
      "upload_id_str": "19983006748",
      "external_id": "69683864-4F2C-450C-B08A-AFE4977EDC8E.fit",
      "from_accepted_tag": false,
      "pr_count": 17,
      "total_photo_count": 0,
      "has_kudoed": false,
      "suffer_score": 110.0
    },
    {
      "resource_state": 2,
      "athlete": {
        "id": 135716013,
        "resource_state": 1
      },
      "name": "Morning Run",
      "distance": 8576.4,
      "moving_time": 2823,
      "elapsed_time": 2827,
      "total_elevation_gain": 10.2,
      "type": "Run",
      "sport_type": "Run",
      "workout_type": null,
      "device_name": "Apple Watch Series 10",
      "id": 18837868592,
      "start_date": "2026-06-08T14:25:05Z",
      "start_date_local": "2026-06-08T10:25:05Z",
      "timezone": "(GMT-05:00) America/New_York",
      "utc_offset": -14400.0,
      "location_city": null,
      "location_state": null,
      "location_country": null,
      "achievement_count": 15,
      "kudos_count": 2,
      "comment_count": 0,
      "athlete_count": 1,
      "photo_count": 0,
      "map": {
        "id": "a18837868592",
        "summary_polyline": "mzvwF`oubM?TXVn@Vl@DTHHRD^BDDDdAZrBf@`Bj@xAb@n@Jp@Rf@Jx@VXLBNmB`GI^HHHEVSN[~@_DRwALm@DIHEDAHD`@^LPFRL`ARXPJr@Pd@Nt@PNFFFBRE~B@d@DTHNLHF?HM@oAJmCJiAF{AD]FElA?p@HVJXF^Vp@TV?^EL@`Ad@f@\\h@f@`@Z^NPGJSlAkCPm@NYHCn@Cv@?^Bh@LD@DH?|@DVBDVCVBLFHX?hA[lCMhEIv@@HDDJDP?JEDI@G?gAJcBFyAPmCLgA^HPAHKRmALEdBL`@HdAPb@B`@?XHb@H|@Vt@PVRj@\\f@Th@NZDdAZdANt@BbB?d@Br@LxA?b@FvBDpAH~AA|@LjADt@Ll@@jAAf@Fz@F|ADfAC~@P`@B`@?j@Dj@?d@BhCDfBRpBNbDL|AHhAAx@NfA@jERhBVx@Ff@JxBVd@JbCRZFnC^rBP`@HhALj@JfAJLDlAn@vAXPA\\MJ?u@ZKAoB_@kAg@m@Ee@Q_C]}@Se@CoAOc@CkAQqAK{AQe@KeAI_AWq@EwAQgACmAIgBGsBQm@@cAI}DQgBKmHY{AKiDK]?[EYUMGIBWLq@FSAe@KiBIa@?o@GkAEm@GaA?u@Ck@@qAKeCKeBCo@EO@m@EWEqAEm@Qa@Su@WeASiAs@q@S}@Qq@I]Iu@E}@Qo@SoAI_Aa@}@Ma@Ko@Eu@FcAAi@OqASq@Gi@@_AUg@IcHy@oBQc@AW@IBKNOn@I|@ETa@v@_@lAQ\\KLOFU?aAQSISMOMIQEa@AEMGMKEMCc@EKQKa@E",
        "resource_state": 2
      },
      "trainer": false,
      "commute": false,
      "manual": false,
      "private": false,
      "visibility": "everyone",
      "flagged": false,
      "gear_id": "g24214689",
      "start_latlng": [
        40.754473,
        -74.007048
      ],
      "end_latlng": [
        40.750506,
        -74.0087
      ],
      "average_speed": 3.038,
      "max_speed": 5.34,
      "average_watts": 182.5,
      "max_watts": 222,
      "weighted_average_watts": 183,
      "device_watts": true,
      "kilojoules": 515.2,
      "has_heartrate": true,
      "average_heartrate": 178.5,
      "max_heartrate": 194.0,
      "heartrate_opt_out": false,
      "display_hide_heartrate_option": true,
      "elev_high": 5.8,
      "elev_low": 0.0,
      "upload_id": 19949049076,
      "upload_id_str": "19949049076",
      "external_id": "9514E1AF-4A59-4370-96BD-7260155B2EA1.fit",
      "from_accepted_tag": false,
      "pr_count": 10,
      "total_photo_count": 0,
      "has_kudoed": false,
      "suffer_score": 146.0
    },
    {
      "resource_state": 2,
      "athlete": {
        "id": 135716013,
        "resource_state": 1
      },
      "name": "Morning Run",
      "distance": 5506.5,
      "moving_time": 1821,
      "elapsed_time": 1853,
      "total_elevation_gain": 12.6,
      "type": "Run",
      "sport_type": "Run",
      "workout_type": null,
      "device_name": "Apple Watch Series 10",
      "id": 18824079882,
      "start_date": "2026-06-07T12:41:09Z",
      "start_date_local": "2026-06-07T08:41:09Z",
      "timezone": "(GMT-05:00) America/New_York",
      "utc_offset": -14400.0,
      "location_city": null,
      "location_state": null,
      "location_country": null,
      "achievement_count": 0,
      "kudos_count": 4,
      "comment_count": 0,
      "athlete_count": 1,
      "photo_count": 0,
      "map": {
        "id": "a18824079882",
        "summary_polyline": "oyvwFxlubM]hA?JBLRPd@L`@Fl@RFHJd@VRd@LVJz@Rd@N`B`@l@VpAb@`Dv@THFF?JoBrGCTFDXAJKdAsDj@{AJMN@XRXDFDBDDj@FHb@Hf@T|@PPGDKRq@b@kAPOf@G`@?z@D~@Lf@Nr@@|AHd@Cp@R|@L|@\\h@HTGTSd@q@RWJg@JKL?lBRv@NFH@H@p@BVHD^FFB?F@bASvCErBKjC@JDFVHPCHK?sAPaCBqBVmC?SRFN?PCLQHy@HOFAt@Hd@L^@XTd@BnARlAFpARtDjBfAVz@TRAf@FrB@n@FhA?z@JvCNjA?xCFnANdAF`A@fEPbC@zAVnBBn@DnA?`BNjCPWKsCCw@Bs@IYGoA@{AQaBGwBCwD[}@?eBO{@@e@MeACc@Dc@?WEcACe@GeAE_A?qBMoAAm@G_BIaAWmAc@m@O}@k@_AY[Gc@EwAYaAIg@M[Ai@SiAMWKy@MkBk@_@A{@Hk@E[Es@Cu@MiAEkA_@",
        "resource_state": 2
      },
      "trainer": false,
      "commute": false,
      "manual": false,
      "private": false,
      "visibility": "everyone",
      "flagged": false,
      "gear_id": "g24214689",
      "start_latlng": [
        40.754322,
        -74.006681
      ],
      "end_latlng": [
        40.745902,
        -74.008446
      ],
      "average_speed": 3.024,
      "max_speed": 5.58,
      "average_watts": 181.3,
      "max_watts": 221,
      "weighted_average_watts": 182,
      "device_watts": true,
      "kilojoules": 330.2,
      "has_heartrate": true,
      "average_heartrate": 176.6,
      "max_heartrate": 191.0,
      "heartrate_opt_out": false,
      "display_hide_heartrate_option": true,
      "elev_high": 6.2,
      "elev_low": -4.0,
      "upload_id": 19934995014,
      "upload_id_str": "19934995014",
      "external_id": "0DF94F9A-FA9A-4631-9CA4-290D91C080E4.fit",
      "from_accepted_tag": false,
      "pr_count": 0,
      "total_photo_count": 0,
      "has_kudoed": false,
      "suffer_score": 88.0
    },
    {
      "resource_state": 2,
      "athlete": {
        "id": 135716013,
        "resource_state": 1
      },
      "name": "Afternoon Run",
      "distance": 5360.1,
      "moving_time": 2150,
      "elapsed_time": 2150,
      "total_elevation_gain": 54.4,
      "type": "Run",
      "sport_type": "Run",
      "workout_type": null,
      "device_name": "Apple Watch Series 10",
      "id": 18804727301,
      "start_date": "2026-06-04T22:21:12Z",
      "start_date_local": "2026-06-04T15:21:12Z",
      "timezone": "(GMT-08:00) America/Los_Angeles",
      "utc_offset": -25200.0,
      "location_city": null,
      "location_state": null,
      "location_country": null,
      "achievement_count": 0,
      "kudos_count": 3,
      "comment_count": 0,
      "athlete_count": 2,
      "photo_count": 0,
      "map": {
        "id": "a18804727301",
        "summary_polyline": "msdiEroejUFAv@NL??IMeA@OHYfAu@^m@nAmAPUb@_AL[F_@A{@@i@\\}BNq@@wADYb@sALWJKHAVFTN\\^FX@ZEdA?r@Bh@E~AE|@O`A@vAEb@Y`AWf@sA|AQf@KRm@n@o@z@c@ZCFDPSx@Ej@JfACd@CJWZITMd@MbAY|@_@r@Qb@{@pAM\\Bp@A`@@`@BNR`@@TCNQt@EZAd@FbACTELCd@Bn@?hBBj@C`BBbAOzDFp@APSj@EXDx@Fd@B\\Pt@Bl@C~@Ub@CV?FJNBLE|@FfAGv@ITOPSHc@Dq@?oAC_ADkBIa@DS?e@KCGFETCbASjCMr@Bx@I^@RGLKNQHYEsCV_BPcBAIKa@Gi@CiAD[Ne@D[YwAc@mACi@L_AQm@Co@BYJa@p@iADQ@S[_BMUWWEMCi@Dq@KcCEk@S{AA_@Jg@Vu@JUv@gAVg@n@k@T]DMFk@@{BGa@Yc@JCVNN\\HHD@V?XCXKDI?WDYLc@?SMK{Ae@]YIQCQ@]J_@LQv@o@l@w@vAwAn@qADWHq@Cc@@s@Ry@XiBC}@Fs@HUf@oALMLANHb@`@P`@BZCfDEr@@d@?n@UpB@~@ATQl@Ul@uAbBg@fAy@z@m@v@YJc@D",
        "resource_state": 2
      },
      "trainer": false,
      "commute": false,
      "manual": false,
      "private": false,
      "visibility": "everyone",
      "flagged": false,
      "gear_id": "g24214689",
      "start_latlng": [
        33.124555,
        -117.178972
      ],
      "end_latlng": [
        33.123649,
        -117.179315
      ],
      "average_speed": 2.493,
      "max_speed": 6.66,
      "average_watts": 155.7,
      "max_watts": 335,
      "weighted_average_watts": 157,
      "device_watts": true,
      "kilojoules": 334.7,
      "has_heartrate": true,
      "average_heartrate": 138.9,
      "max_heartrate": 170.0,
      "heartrate_opt_out": false,
      "display_hide_heartrate_option": true,
      "elev_high": 202.6,
      "elev_low": 169.4,
      "upload_id": 19915277702,
      "upload_id_str": "19915277702",
      "external_id": "CD5E5C4F-A1D5-4C3B-94C9-F273233901EC.fit",
      "from_accepted_tag": false,
      "pr_count": 0,
      "total_photo_count": 0,
      "has_kudoed": false,
      "suffer_score": 19.0
    },
    {
      "resource_state": 2,
      "athlete": {
        "id": 135716013,
        "resource_state": 1
      },
      "name": "Morning Run",
      "distance": 14252.0,
      "moving_time": 5479,
      "elapsed_time": 5586,
      "total_elevation_gain": 61.0,
      "type": "Run",
      "sport_type": "Run",
      "workout_type": null,
      "device_name": "Apple Watch Series 10",
      "id": 18758733907,
      "start_date": "2026-06-02T15:47:37Z",
      "start_date_local": "2026-06-02T08:47:37Z",
      "timezone": "(GMT-08:00) America/Los_Angeles",
      "utc_offset": -25200.0,
      "location_city": null,
      "location_state": null,
      "location_country": null,
      "achievement_count": 0,
      "kudos_count": 4,
      "comment_count": 0,
      "athlete_count": 1,
      "photo_count": 0,
      "map": {
        "id": "a18758733907",
        "summary_polyline": "cfyhEtsoiUTOt@[PMJ[Bq@H_@`AkALWJ{@@_@Cy@@g@Jq@Ps@?OEEc@AaB]}Ac@e@UeAq@a@O{Be@q@@KCEOGq@W{AgAwCEi@FUJIH@tBr@vA`@r@Xx@T`Bn@`B^|@ZjIrBnHdAZB^ALCRKb@o@Pm@\\{CViBh@_Cp@iEJe@^oAReA\\a@VM\\Cz@FPIJe@Xy@?iALg@RWp@c@HIVy@`ByDzCoIH_@NeB`AgIJuAFcA@aDEoAEcMMiCo@aGm@_HOeAu@qCy@uDqA{Di@gAIU?IDOp@qAHg@@a@A_@QiAJw@Aa@DR?YI[MYOOe@WQc@OcA]uA}@aEi@iBYwAUy@[q@Co@Mq@aBcHG}@?_FG}DMQYGM@QLSBgDe@k@W[[SIK?i@Vk@JgC@{@LeCRo@?gAFkAT]@k@FcA@cBLeCDa@I_D?y@EwCFgCKkA]]G{@c@g@I}@WIGUCQKY]WKa@Ku@KQOe@aAW[[S_@Mo@IkBHu@LiAZWBSAq@Mw@[i@KaC}@u@[kBa@m@[}Ag@g@Wc@YMMm@y@k@k@MUCQDBNACFC?Zd@j@l@h@r@RL`Ad@hA`@b@ThCr@jCbAnA\\l@Xz@PT@TC|@Y~@MnBGv@L`@N\\X|@lATHz@JVJLLZd@LHtAb@z@NbCx@f@HvCLvBKv@FrBEfANv@EpAAnBQjCM~@St@Ex@BnEc@`C?TEv@]PENDn@h@ZJtBZj@DPA`@ON?PHJPDT@lCC`EBpALfAb@fBVjAX~@Lh@F\\Br@Zt@r@vCJZzBxJPr@HNHF\\RJLNl@@l@Mn@APRz@B\\?XKp@s@xAER?JZf@`@z@^dAl@rB^bBz@`DRjAPxAVlCNlBd@hENrBDdBBdG@jHBfBAd@cArIW|BEv@O|@wArDI\\aCbGk@~AQTe@\\[`@Kb@CnAe@tAEDKDm@Ke@B]N]`@Ov@Od@YnAc@lC{@|D[jCSzBUr@Yd@UNUFu@@oG_AgE}@aDy@_A[{@SmBm@{CiAoDeAWCMDEBCTDZJZh@nARl@X|AHt@DPNFZEh@B|A\\~@^~Az@bCl@dAPHBJJARUt@Kx@?vBQjAKP}@~@ENK`AO\\OHiAb@",
        "resource_state": 2
      },
      "trainer": false,
      "commute": false,
      "manual": false,
      "private": false,
      "visibility": "everyone",
      "flagged": false,
      "gear_id": "g24214689",
      "start_latlng": [
        33.066107,
        -117.066985
      ],
      "end_latlng": [
        33.066116,
        -117.066974
      ],
      "average_speed": 2.601,
      "max_speed": 3.72,
      "average_watts": 159.2,
      "max_watts": 281,
      "weighted_average_watts": 160,
      "device_watts": true,
      "kilojoules": 872.4,
      "has_heartrate": true,
      "average_heartrate": 146.8,
      "max_heartrate": 179.0,
      "heartrate_opt_out": false,
      "display_hide_heartrate_option": true,
      "elev_high": 107.2,
      "elev_low": 97.2,
      "upload_id": 19868466315,
      "upload_id_str": "19868466315",
      "external_id": "46123291-9148-456B-9286-98DCE7434AC3.fit",
      "from_accepted_tag": false,
      "pr_count": 0,
      "total_photo_count": 0,
      "has_kudoed": false,
      "suffer_score": 71.0
    },
    {
      "resource_state": 2,
      "athlete": {
        "id": 135716013,
        "resource_state": 1
      },
      "name": "Over and Unders Miles",
      "distance": 5828.7,
      "moving_time": 1963,
      "elapsed_time": 1986,
      "total_elevation_gain": 39.5,
      "type": "Run",
      "sport_type": "Run",
      "workout_type": null,
      "device_name": "Runna",
      "id": 18743268428,
      "start_date": "2026-06-01T15:13:27Z",
      "start_date_local": "2026-06-01T08:13:27Z",
      "timezone": "(GMT-08:00) America/Los_Angeles",
      "utc_offset": -25200.0,
      "location_city": null,
      "location_state": null,
      "location_country": null,
      "achievement_count": 0,
      "kudos_count": 4,
      "comment_count": 0,
      "athlete_count": 1,
      "photo_count": 0,
      "map": {
        "id": "a18743268428",
        "summary_polyline": "agyhE|{oiUJY@KCGSOE[CE[GKFCCb@}@Vu@Xm@b@[b@IXUJY?KBg@\\o@NIj@y@Jg@D]EyAHiANq@HY?GGIE?Q?QAm@Oe@EwAc@cAg@c@[_@Sc@KqBc@m@HIEOo@KqAOe@CS_@q@Qa@Ka@Gc@@SJW`@D~@\\ZFh@TL@FDH@FD^Hn@\\l@JND@FH?NHJ@HFr@NHF|Ab@LHh@HLFJ?^PPBHDR@NHz@TBBN?d@JJDb@HTHXFN@d@JX?^Hx@HlBZr@DJ?TKl@y@XiAHgARoA@e@Lu@VcANI?N[^Ql@ANCJc@bEYrAY^QNODa@Be@Cg@IM?[GYIu@Go@OOAw@OYAKG_@IIEKAaAUOCOG{@OQG]Gm@Ue@Ia@SqAYIGgBk@q@[k@OGGUG?JHDP?RJj@RBB^FHHRHVDd@Rz@Pb@RXFNJd@FVLbAVBBRBRHJ?FDb@DBD|@RDB|AXR@^FX@HDRBDBR?`@FPDR@jARb@BRAJEFIHGBIV[FQR_ATaCJo@@[XmAWv@MxACDATIh@G`AWbAKZa@^WHc@@E@c@IE@cAQOEg@EG?kASWCECE@y@U]EWKE@_Be@g@IG@m@WMAG?CCe@MQIG?{@YABJLZBz@XF?JDZDTJBCRJP@RJJ?VJVBJFBAHDNBTHH@BECEU?IGe@KE@SGYEo@QYM[EUKgAWMGmBc@IG[IOKKASK[Kc@SI?UKYIi@SQCQKYECE{@SOGMCI?ODGFATDb@j@nAVr@Jf@D\\L`@?JJx@DFFD^IX?XF`@LNB\\LDALFTBz@d@JJXPr@RJ?JFLBBB\\HHDR?BDN?LFr@HJH@DCNIPIZO`AARBvAKrAINu@p@QXI\\CX",
        "resource_state": 2
      },
      "trainer": false,
      "commute": false,
      "manual": false,
      "private": false,
      "visibility": "everyone",
      "flagged": false,
      "gear_id": "g24214689",
      "start_latlng": [
        33.066258,
        -117.068301
      ],
      "end_latlng": [
        33.065579,
        -117.066493
      ],
      "average_speed": 2.969,
      "max_speed": 5.4,
      "average_cadence": 87.0,
      "average_watts": 179.4,
      "max_watts": 245,
      "weighted_average_watts": 183,
      "device_watts": true,
      "kilojoules": 352.1,
      "has_heartrate": true,
      "average_heartrate": 157.0,
      "max_heartrate": 180.0,
      "heartrate_opt_out": false,
      "display_hide_heartrate_option": true,
      "elev_high": 104.7,
      "elev_low": 97.5,
      "upload_id": 19852731195,
      "upload_id_str": "19852731195",
      "external_id": "42B8AE88-99EE-4FC7-9FA2-227960734DD7.fit",
      "from_accepted_tag": false,
      "pr_count": 0,
      "total_photo_count": 1,
      "has_kudoed": false,
      "suffer_score": 45.0
    },
    {
      "resource_state": 2,
      "athlete": {
        "id": 135716013,
        "resource_state": 1
      },
      "name": "Afternoon Run",
      "distance": 5402.2,
      "moving_time": 2286,
      "elapsed_time": 2289,
      "total_elevation_gain": 64.2,
      "type": "Run",
      "sport_type": "Run",
      "workout_type": null,
      "device_name": "Apple Watch Series 10",
      "id": 18708664310,
      "start_date": "2026-05-29T23:57:28Z",
      "start_date_local": "2026-05-29T16:57:28Z",
      "timezone": "(GMT-08:00) America/Los_Angeles",
      "utc_offset": -25200.0,
      "location_city": null,
      "location_state": null,
      "location_country": null,
      "achievement_count": 0,
      "kudos_count": 4,
      "comment_count": 0,
      "athlete_count": 3,
      "photo_count": 0,
      "map": {
        "id": "a18708664310",
        "summary_polyline": "_tdiExnejU@NHH\\Hp@H@IKa@COBa@FSVYt@i@f@u@hAkAZc@`@cAF[@YC]B{@TiAFe@ReACs@Fm@Pq@^y@LKFAN@b@\\PPHXF\\K|ABjAE~AUbCBhACXe@dBMTiArAYr@MRs@p@c@n@a@XEFBNANSh@Gd@@`@FbAC\\GLONIPOr@Ef@[hAe@z@Sj@cAvAEPB~BHRLL@PCZS`ACv@BlAG\\CVDX@b@CfGBt@QfDLz@CLQd@EXJxBDVRx@@Z?h@CVW^EXBPDF@J?j@Dl@AbACXGVKTMDUFaABqE@{@GWFMA[GO?EEBE^Gd@O~AEnAKl@Dd@Gr@?PILKNWDM?KCc@@a@AuAb@eDMiAGkB@URo@BSWgAE_@We@GW?i@J{@Qo@Cg@Dg@DSRa@`@m@DO@OAS]_B]c@Kg@ASFaAAYIkB[_C?_@HYn@}A^c@j@_Ah@e@LSLYDg@@wBKk@SY@GDAVHHHL^PHP?VGTMDGB_@R{@@QCCiBe@YUISE]?OFe@BKJKz@o@p@{@lAkALSRc@Pg@FYBY?w@Bi@XiBR{@@a@Ai@Di@h@_BNQNAZL^^LZD\\GnA@b@EdDA`@WpBDt@CXMf@c@hAa@j@i@h@ILUl@{@`AIR@BGMIC[D",
        "resource_state": 2
      },
      "trainer": false,
      "commute": false,
      "manual": false,
      "private": false,
      "visibility": "everyone",
      "flagged": false,
      "gear_id": "g24214689",
      "start_latlng": [
        33.12464,
        -117.178842
      ],
      "end_latlng": [
        33.123363,
        -117.179027
      ],
      "average_speed": 2.363,
      "max_speed": 4.44,
      "average_watts": 145.9,
      "max_watts": 248,
      "weighted_average_watts": 148,
      "device_watts": true,
      "kilojoules": 333.6,
      "has_heartrate": true,
      "average_heartrate": 138.2,
      "max_heartrate": 161.0,
      "heartrate_opt_out": false,
      "display_hide_heartrate_option": true,
      "elev_high": 207.0,
      "elev_low": 169.2,
      "upload_id": 19817431789,
      "upload_id_str": "19817431789",
      "external_id": "24B1B881-BB86-4A55-AFEC-27DA8B53A540.fit",
      "from_accepted_tag": false,
      "pr_count": 0,
      "total_photo_count": 0,
      "has_kudoed": false,
      "suffer_score": 12.0
    },
    {
      "resource_state": 2,
      "athlete": {
        "id": 135716013,
        "resource_state": 1
      },
      "name": "Lunch Run",
      "distance": 19546.8,
      "moving_time": 6363,
      "elapsed_time": 6370,
      "total_elevation_gain": 71.6,
      "type": "Run",
      "sport_type": "Run",
      "workout_type": null,
      "device_name": "Apple Watch Series 10",
      "id": 18693940808,
      "start_date": "2026-05-28T18:16:41Z",
      "start_date_local": "2026-05-28T11:16:41Z",
      "timezone": "(GMT-08:00) America/Los_Angeles",
      "utc_offset": -25200.0,
      "location_city": null,
      "location_state": null,
      "location_country": null,
      "achievement_count": 0,
      "kudos_count": 5,
      "comment_count": 0,
      "athlete_count": 1,
      "photo_count": 0,
      "map": {
        "id": "a18693940808",
        "summary_polyline": "wfyhEftoiU\\]x@_@XSFOBo@Je@z@}@LUPqAAqBNeAPm@?OIGi@CiDu@aCsA_@KcB_@kAE]aCuA}DAYBUPM`@HjLvD`NhDhHbAf@C\\Od@o@VaAl@wFt@aDr@gENo@LUVqAZa@ZMZCj@FTAFGb@wADqAF]Vc@l@_@NSnGuPJe@\\wD~@}HHmDOsRGkA}AsPWmBy@qCoAeF_@kAgAgC@Sv@{AJc@@_@Eo@Oy@Js@@k@Uu@s@e@KQO_AuB_JgAsEUe@IaAgBqHM}@KoLISSIW@UNSByCc@k@Yk@g@MEm@Xs@RqCAs@NcCR}BH}@TkCHkAJeDFw@MaBDmBGqDFcBMgDiAq@KkA]OIc@k@mBc@USo@mAYWUKsAQkBNmBf@e@BeAWg@Wq@KcDoAuBi@aC{@uAw@US}A}BEEGFBLz@r@dAlAjAl@rCdA~A^bDlA`AVb@TrAVdCi@dCMn@Ln@ZpA`BnBb@p@x@tAd@z@NzBr@v@Nv@FlC@r@GpBFtACdANdBGnG]rAWjDK`CYvCAjAe@PBh@h@h@RzC^r@SL?TLJPAvKJtAdB|HHz@d@lApDbON|@LVp@`@Rj@@t@K`APbA?~@Ih@w@`BFGn@{AH_@Be@Cm@ScALw@@g@So@u@i@KSWsAcBuHoA}EYo@GaAoBkIEe@EoH@gBE_@KMe@Ai@RoCa@w@Yk@k@MEcBn@oCAu@NsFVmAXsAJeHPs@KcBDsBIiDHkBOaBe@g@W_Dw@k@m@UK{AYOM_AaBe@YcAOi@?qALoBh@c@@_AUs@Yc@I{DwAyA[iCcAaB}@y@gAUe@e@a@?JJPn@f@fAlApAr@fBj@b@V`B`@bFbBd@VfAT`@AfA]r@M|BGf@Hv@\\VX\\n@XThB\\PLVd@LJrAd@~@P~@^hBd@~AJlDIv@FbCCdANjBEhGa@vAYpABlEc@hCAbBg@RFl@d@d@NtCb@ZCh@OJDLPBX@tB?bHDn@fBvHNnAh@|AdAvEX~@xAzGT`@l@ZP^@x@KdAPjAAbAI^s@vAAZt@rA^dAt@hCtAnFRbApBnSFvBFdTKlBy@lGc@vEwCbIiCnGs@n@U`@Kf@ElAa@fAKLKBs@K]Bg@XQXOz@c@zAi@fD_AdEy@xGQf@]\\c@Ni@@uIsA{D}@gGcBiIsC",
        "resource_state": 2
      },
      "trainer": false,
      "commute": false,
      "manual": false,
      "private": false,
      "visibility": "everyone",
      "flagged": false,
      "gear_id": "g24214689",
      "start_latlng": [
        33.066204,
        -117.067076
      ],
      "end_latlng": [
        33.067651,
        -117.061368
      ],
      "average_speed": 3.072,
      "max_speed": 4.44,
      "average_watts": 184.9,
      "max_watts": 301,
      "weighted_average_watts": 185,
      "device_watts": true,
      "kilojoules": 1176.2,
      "has_heartrate": true,
      "average_heartrate": 170.0,
      "max_heartrate": 195.0,
      "heartrate_opt_out": false,
      "display_hide_heartrate_option": true,
      "elev_high": 109.0,
      "elev_low": 98.6,
      "upload_id": 19802428219,
      "upload_id_str": "19802428219",
      "external_id": "16D1E195-C92B-476C-A0D0-F01799E9C9AE.fit",
      "from_accepted_tag": false,
      "pr_count": 0,
      "total_photo_count": 0,
      "has_kudoed": false,
      "suffer_score": 253.0
    },
    {
      "resource_state": 2,
      "athlete": {
        "id": 135716013,
        "resource_state": 1
      },
      "name": "Lunch Run",
      "distance": 6194.3,
      "moving_time": 2057,
      "elapsed_time": 2271,
      "total_elevation_gain": 42.2,
      "type": "Run",
      "sport_type": "Run",
      "workout_type": null,
      "device_name": "Apple Watch Series 10",
      "id": 18665874177,
      "start_date": "2026-05-26T19:02:44Z",
      "start_date_local": "2026-05-26T12:02:44Z",
      "timezone": "(GMT-08:00) America/Los_Angeles",
      "utc_offset": -25200.0,
      "location_city": null,
      "location_state": null,
      "location_country": null,
      "achievement_count": 0,
      "kudos_count": 3,
      "comment_count": 0,
      "athlete_count": 1,
      "photo_count": 0,
      "map": {
        "id": "a18665874177",
        "summary_polyline": "yfyhEhtoiUHOPQ^SXIZWL[?]He@|@eANYJc@B_@?g@Em@@a@NaAPo@@KKGg@EwBc@y@U[MsA{@o@UiBa@SA_@BMEGQYqBQq@Y{@Wk@K_@Ca@DQLIP@hBl@|@TfBr@jA^pCv@jCx@rEhAxAXvDf@nATZBR?TCRILO`@s@Pu@r@{Ft@gDh@gDZkAJ[P_APYTQJEXCx@DJALIb@wABqAH]FQPSn@c@f@cAnBqFtBmFRw@\\sDTaBDi@XyBRoC@cBIqQAlDH~I@pDOlBi@`Ee@jEEj@Ij@gArCsArDwBhFS^i@`@Yd@Id@CjAc@pAKDO@k@Ge@DOFOJU\\Kb@AVGDEPYjAq@hEq@tCs@~FSt@Q\\UPQFYD_@?eIkAuG}AeBk@_Ba@yBy@QEaAa@w@QoC{@OCI@OLCTDZHVd@dAZ|@VnAJbAHPHB\\IT@`Cd@`CpA|Bj@`B\\NH@DAL",
        "resource_state": 2
      },
      "trainer": false,
      "commute": false,
      "manual": false,
      "private": false,
      "visibility": "everyone",
      "flagged": false,
      "gear_id": "g24214689",
      "start_latlng": [
        33.066211,
        -117.067087
      ],
      "end_latlng": [
        33.064864,
        -117.064217
      ],
      "average_speed": 3.011,
      "max_speed": 4.64,
      "average_watts": 183.6,
      "max_watts": 367,
      "weighted_average_watts": 179,
      "device_watts": true,
      "kilojoules": 377.7,
      "has_heartrate": true,
      "average_heartrate": 164.9,
      "max_heartrate": 189.0,
      "heartrate_opt_out": false,
      "display_hide_heartrate_option": true,
      "elev_high": 109.2,
      "elev_low": 98.8,
      "upload_id": 19773844441,
      "upload_id_str": "19773844441",
      "external_id": "E1C1FAD3-7390-40B1-9F3E-50057CA64C72.fit",
      "from_accepted_tag": false,
      "pr_count": 0,
      "total_photo_count": 0,
      "has_kudoed": false,
      "suffer_score": 68.0
    },
    {
      "resource_state": 2,
      "athlete": {
        "id": 135716013,
        "resource_state": 1
      },
      "name": "Night Run",
      "distance": 6200.0,
      "moving_time": 2405,
      "elapsed_time": 2405,
      "total_elevation_gain": 0,
      "type": "Run",
      "sport_type": "Run",
      "workout_type": null,
      "device_name": "Apple Watch Series 10",
      "id": 18656592544,
      "start_date": "2026-05-26T04:31:46Z",
      "start_date_local": "2026-05-25T21:31:46Z",
      "timezone": "(GMT-07:00) America/Creston",
      "utc_offset": -25200.0,
      "location_city": null,
      "location_state": null,
      "location_country": null,
      "achievement_count": 0,
      "kudos_count": 5,
      "comment_count": 0,
      "athlete_count": 1,
      "photo_count": 0,
      "map": {
        "id": "a18656592544",
        "summary_polyline": "",
        "resource_state": 2
      },
      "trainer": true,
      "commute": false,
      "manual": false,
      "private": false,
      "visibility": "everyone",
      "flagged": false,
      "gear_id": "g24214689",
      "start_latlng": [],
      "end_latlng": [],
      "average_speed": 2.578,
      "max_speed": 2.9,
      "has_heartrate": true,
      "average_heartrate": 137.5,
      "max_heartrate": 152.0,
      "heartrate_opt_out": false,
      "display_hide_heartrate_option": true,
      "elev_high": 0.0,
      "elev_low": 0.0,
      "upload_id": 19764408359,
      "upload_id_str": "19764408359",
      "external_id": "C493E42D-3361-4242-B2D4-D107F0016A22.fit",
      "from_accepted_tag": false,
      "pr_count": 0,
      "total_photo_count": 0,
      "has_kudoed": false,
      "suffer_score": 14.0
    }
  ]
}